ratpack/__init__.py
ratpack/infest.py
ratpack/images/rat1.png
ratpack/images/rat10.png
ratpack/images/rat2.png
ratpack/images/rat3.png
ratpack/images/rat4.png
ratpack/images/rat5.png
ratpack/images/rat6.png
ratpack/images/rat7.png
ratpack/images/rat8.png
ratpack/images/rat9.png
ratpack-0.1.3.dist-info/licenses/LICENSE
ratpack-0.1.3.dist-info/METADATA
ratpack-0.1.3.dist-info/WHEEL
ratpack-0.1.3.dist-info/entry_points.txt
ratpack-0.1.3.dist-info/top_level.txt
ratpack-0.1.3.dist-info/RECORD
