Metadata-Version: 2.4
Name: ratpack
Version: 0.1.3
Summary: A humorous Python package that simulates rat infestations in your code! It provides tools to create, count, visualize, and exterminate virtual rat infestations represented as files on your filesystem.
Author-email: Patrick Cao <pc3135@nyu.edu>, Helen Ho <hth2016@nyu.edu>, Noah Perelmuter <np2446@nyu.edu>, Apollo Wyndham <acw8241@nyu.edu>
License:                     GNU GENERAL PUBLIC LICENSE
Project-URL: Homepage, https://github.com/software-students-spring2025/3-python-package-team-1
Project-URL: Repository, https://github.com/software-students-spring2025/3-python-package-team-1.git
Project-URL: Bug Tracker, https://github.com/software-students-spring2025/3-python-package-team-1/issues
Project-URL: Documentation, https://github.com/software-students-spring2025/3-python-package-team-1/blob/main/README.md
Keywords: python,package,rat,infestation,decorator,filesystem
Classifier: Programming Language :: Python :: 3
Classifier: Programming Language :: Python :: 3.7
Classifier: Programming Language :: Python :: 3.8
Classifier: Programming Language :: Python :: 3.9
Classifier: Programming Language :: Python :: 3.10
Classifier: Programming Language :: Python :: 3.11
Classifier: Intended Audience :: Developers
Classifier: Intended Audience :: Education
Classifier: License :: OSI Approved :: GNU General Public License v3 (GPLv3)
Classifier: Operating System :: OS Independent
Classifier: Topic :: Software Development :: Libraries :: Python Modules
Classifier: Topic :: Education
Classifier: Topic :: Utilities
Requires-Python: >=3.7
License-File: LICENSE
Requires-Dist: pillow>=9.0.0
Provides-Extra: dev
Requires-Dist: pytest>=7.0.0; extra == "dev"
Requires-Dist: build>=0.9.0; extra == "dev"
Requires-Dist: twine>=4.0.0; extra == "dev"
Dynamic: license-file
